README.md
setup.py
gruut_lang_ca/VERSION
gruut_lang_ca/__init__.py
gruut_lang_ca/lexicon.db
gruut_lang_ca.egg-info/PKG-INFO
gruut_lang_ca.egg-info/SOURCES.txt
gruut_lang_ca.egg-info/dependency_links.txt
gruut_lang_ca.egg-info/top_level.txt
gruut_lang_ca/g2p/model.crf