Metadata-Version: 2.1
Name: gruut_lang_ca
Version: 2.0.1
Summary: Catalan language files for gruut tokenizer/phonemizer
Home-page: https://github.com/rhasspy/gruut
Author: Michael Hansen
Author-email: mike@rhasspy.org
Classifier: Programming Language :: Python :: 3
Classifier: License :: OSI Approved :: MIT License
